[
  {
    "id": 1,
    "country": {
      "id": 0,
      "name": "Italia"
    },
    "url": "https://www.giorgettimeda.com/it/events-news/london-design-week-2021",
    "image": "/giorgetti/img/news/7707_t_Giorgetti_invitation_LondonDesignWeek_202105.jpg",
    "date": "10.5.2021",
    "title": "Visita il Giorgetti Store di Londra durante la Design Week",
    "abstract": "Dal 17 al 21 maggio, fra icone del brand e nuove collezioni, Giorgetti London mette in scena il suo lifestyle."
  },
  {
    "id": 1,
    "country": {
      "id": 0,
      "name": "Italia"
    },
    "url": "https://www.giorgettimeda.com/it/events-news/giorgetti-catalogue-places-to-live",
    "image": "/giorgetti/img/news/7660_t_news.jpg",
    "date": "19.4.2021",
    "title": "Giorgetti presenta il nuovo catalogo “Places To Live”",
    "abstract": "Le nuove collezioni Giorgetti si raccontano in un’esperienza emozionale."
  },
  {
    "id": 1,
    "country": {
      "id": 0,
      "name": "Italia"
    },
    "url": "https://www.giorgettimeda.com/it/events-news/giorgetti-news-discover-houdini",
    "image": "/giorgetti/img/news/7645_t_news.jpg",
    "date": "12.4.2021",
    "title": "Discover Houdini",
    "abstract": "New collection 2021: tradizione ebanistica."
  },
  {
    "id": 1,
    "country": {
      "id": 0,
      "name": "Italia"
    },
    "url": "https://www.giorgettimeda.com/it/events-news/giorgetti-milano-design-city-2021",
    "image": "/giorgetti/img/news/7632_t_INVITO_MilanoDesignCity_2021.jpg",
    "date": "12.4.2021",
    "title": "Milano Design City 2021: Giorgetti rinnova l’Atelier e lo Store di Milano",
    "abstract": "Dal 12 al 23 aprile, fra icone del brand e nuove collezioni, Giorgetti mette in scena il suo lifestyle."
  },
  {
    "id": 1,
    "country": {
      "id": 0,
      "name": "Italia"
    },
    "url": "https://www.giorgettimeda.com/it/events-news/giorgetti-bilancio-sostenibilita",
    "image": "/giorgetti/img/news/7501_z_news-big.jpg",
    "date": "9.3.2021",
    "title": "Giorgetti presenta il primo bilancio di sostenibilità",
    "abstract": "Raggiungere i SDGs definiti dall’Onu per un futuro migliore."
  },
  {
    "id": 1,
    "country": {
      "id": 0,
      "name": "Italia"
    },
    "url": "https://www.giorgettimeda.com/it/events-news/giorgetti-presenta-houdini",
    "image": "/giorgetti/img/news/7616_t_Giorgetti_news-Houdini1_listing.jpg",
    "date": "6.4.2021",
    "title": "Giorgetti presenta Houdini",
    "abstract": "New collection 2021: una scatola delle meraviglie."
  },
  {
    "id": 1,
    "country": {
      "id": 0,
      "name": "Italia"
    },
    "url": "https://www.giorgettimeda.com/it/events-news/giorgetti-spazio-casablanca",
    "image": "/giorgetti/img/news/7525_t_Giorgetti_Store-Casablanca-Klarte_listing.jpg",
    "date": "18.3.2021",
    "title": "Giorgetti arriva a Casablanca",
    "abstract": "Giorgetti porta il Made in Italy in Marocco."
  },
  {
    "id": 1,
    "country": {
      "id": 0,
      "name": "Italia"
    },
    "url": "https://www.giorgettimeda.com/it/events-news/giorgetti-store-losangeles-opening",
    "image": "/giorgetti/img/news/7562_t_Giorgetti_news_LA-2_listing.jpg",
    "date": "16.3.2021",
    "title": "Giorgetti apre un nuovo spazio a Los Angeles",
    "abstract": "Giorgetti da Robina Benson Design House, Melrose Ave"
  },
  {
    "id": 1,
    "country": {
      "id": 0,
      "name": "Italia"
    },
    "url": "https://www.giorgettimeda.com/it/events-news/collezione-2020-giorgetti-london",
    "image": "/giorgetti/img/news/7533_t_Giorgetti_news_LDN_listing2.jpg",
    "date": "16.3.2021",
    "title": "Nuovi prodotti dell’ultima collezione nello Store Giorgetti di Londra",
    "abstract": "Giorgetti a Fulham Road, Londra."
  },
  {
    "id": 1,
    "country": {
      "id": 0,
      "name": "Italia"
    },
    "url": "https://www.giorgettimeda.com/it/events-news/miyabi-cabina-armadio-sanificatore",
    "image": "/giorgetti/img/news/7460_t_Giorgetti_AtelierMilano_2020_news.jpg",
    "date": "17.2.2021",
    "title": "Miyabi, la cabina armadio con sanificatore",
    "abstract": "La tecnologia IPG."
  },
  {
    "id": 1,
    "country": {
      "id": 0,
      "name": "Italia"
    },
    "url": "https://www.giorgettimeda.com/it/events-news/giorgetti-per-audemars-piguet",
    "image": "/giorgetti/img/news/7428_t_Giorgetti_Barcelona_Audemas-Piguet_news.jpg",
    "date": "3.2.2021",
    "title": "Giorgetti per Audemars Piguet",
    "abstract": "Giorgetti nella AP House di Barcellona."
  },
  {
    "id": 1,
    "country": {
      "id": 0,
      "name": "Italia"
    },
    "url": "https://www.giorgettimeda.com/it/events-news/clop-wallpaper-design-awards-2021",
    "image": "/giorgetti/img/news/7414_t_news.jpg",
    "date": "8.1.2021",
    "title": "Giorgetti vince i Wallpaper Design Awards",
    "abstract": "Con la seduta a dondolo Clop, il brand è protagonista della categoria Best Outdoor Entertaining."
  },
  {
    "id": 1,
    "country": {
      "id": 0,
      "name": "Italia"
    },
    "url": "https://www.giorgettimeda.com/it/events-news/giorgetti-per-il-progetto-quirinale-contemporaneo",
    "image": "/giorgetti/img/news/7407_t_news.jpg",
    "date": "19.12.2020",
    "title": "Giorgetti per il progetto Quirinale Contemporaneo",
    "abstract": "Mobius di Umberto Asnago nel Palazzo della Presidenza della Repubblica Italiana."
  },
  {
    "id": 1,
    "country": {
      "id": 0,
      "name": "Italia"
    },
    "url": "https://www.giorgettimeda.com/it/events-news/giorgetti-2020",
    "image": "/giorgetti/img/news/7389_t_news.jpg",
    "date": "17.12.2020",
    "title": "Rivivi con noi il nostro 2020",
    "abstract": "Il 2020 è stato teatro di molti avvenimenti, con l'opportunità di pensare, riflettere e pianificare il futuro con una nuova prospettiva."
  },
  {
    "id": 1,
    "country": {
      "id": 0,
      "name": "Italia"
    },
    "url": "https://www.giorgettimeda.com/it/events-news/giorgetti-holidays",
    "image": "/giorgetti/img/news/7410_t_news.jpg",
    "date": "16.12.2020",
    "title": "Giorgetti holidays",
    "abstract": "Le feste, in stile Giorgetti."
  },
  {
    "id": 1,
    "country": {
      "id": 0,
      "name": "Italia"
    },
    "url": "https://www.giorgettimeda.com/it/events-news/giorgetti-store-london-opening",
    "image": "/giorgetti/img/news/7358_t_news.jpg",
    "date": "16.12.2020",
    "title": "Giorgetti apre un monobrand a Londra",
    "abstract": "Sviluppato su due livelli, lo store ha una superficie totale di 400 metri quadrati."
  },
  {
    "id": 1,
    "country": {
      "id": 0,
      "name": "Italia"
    },
    "url": "https://www.giorgettimeda.com/it/events-news/giorgetti-rene-caovilla",
    "image": "/giorgetti/img/news/7327_t_news.jpg",
    "date": "10.12.2020",
    "title": "Giorgetti e René Caovilla",
    "abstract": "Un incontro tra eccellenze italiane."
  },
  {
    "id": 1,
    "country": {
      "id": 0,
      "name": "Italia"
    },
    "url": "https://www.giorgettimeda.com/it/events-news/cuckoo-clock-best-of-year",
    "image": "/giorgetti/img/news/7300_t_news.jpg",
    "date": "9.12.2020",
    "title": "Cuckoo Clock è 2020 Best of Year",
    "abstract": "Cuckoo Clock di Virginia Harper riceve il Best of Year 2020 Award."
  },
  {
    "id": 1,
    "country": {
      "id": 0,
      "name": "Italia"
    },
    "url": "https://www.giorgettimeda.com/it/events-news/battaglia-signature-kitchen-suite",
    "image": "/giorgetti/img/news/7240_t_Giorgetti_2-SKS_Ground-Floor_reception_2_HR-news.jpg",
    "date": "4.12.2020",
    "title": "Battaglia per Signature Kitchen Suite",
    "abstract": "Battaglia è developer del primo showroom europeo di Signature Kitchen Suite."
  },
  {
    "id": 1,
    "country": {
      "id": 0,
      "name": "Italia"
    },
    "url": "https://www.giorgettimeda.com/it/events-news/giorgetti-company-update-sedi-e-store",
    "image": "/giorgetti/img/news/7192_t_Giorgetti_AtelierMilano_2020_588_HR_news.jpg",
    "date": "9.11.2020",
    "title": "Company update | sedi e store",
    "abstract": "9 novembre 2020."
  },
  {
    "id": 1,
    "country": {
      "id": 0,
      "name": "Italia"
    },
    "url": "https://www.giorgettimeda.com/it/events-news/giorgetti-usa-the-centrale-ny",
    "image": "/giorgetti/img/news/7168_t_Giorgetti_NY_TheCentrale_Rich-Caplan-ph_138E50_5_listing.jpg",
    "date": "28.10.2020",
    "title": "Nuovi headquarters per Giorgetti USA @ The Centrale, NY",
    "abstract": "Una dimora esclusiva presso la Midtown Condominium Tower, a New York."
  },
  {
    "id": 1,
    "country": {
      "id": 0,
      "name": "Italia"
    },
    "url": "https://www.giorgettimeda.com/it/events-news/giorgetti-imade-2020-revolutionary-icons",
    "image": "/giorgetti/img/news/7148_t_Giorgetti_IMADE2020_news.jpg",
    "date": "28.9.2020",
    "title": "Revolutionary Icons",
    "abstract": "Giorgetti nella mostra virtuale di I-MADE su Artemest.com."
  },
  {
    "id": 1,
    "country": {
      "id": 0,
      "name": "Italia"
    },
    "url": "https://www.giorgettimeda.com/it/events-news/giorgetti-salone-nautico-genova-2020",
    "image": "/giorgetti/img/news/7139_t_Giorgetti_Genova2020_cover-news.jpg",
    "date": "25.9.2020",
    "title": "Giorgetti è al Salone Nautico di Genova",
    "abstract": "Dal 1 al 6 ottobre 2020, Giorgetti arreda la VIP Lounge."
  },
  {
    "id": 1,
    "country": {
      "id": 0,
      "name": "Italia"
    },
    "url": "https://www.giorgettimeda.com/it/events-news/giorgetti-new-collection-2020",
    "image": "/giorgetti/img/news/7092_t_news.jpg",
    "date": "17.9.2020",
    "title": "New Collection 2020",
    "abstract": "Su “Voices” di Giorgetti Channel, la nuova collezione 2020."
  },
  {
    "id": 1,
    "country": {
      "id": 0,
      "name": "Italia"
    },
    "url": "https://www.giorgettimeda.com/it/events-news/milano-design-city-2020-giorgetti-atelier-store",
    "image": "/giorgetti/img/news/7097_t_Giorgetti_AtelierMilano_2020_410_HR_news.jpg",
    "date": "14.9.2020",
    "title": "Milano Design City 2020: Giorgetti rinnova Atelier e Store di Milano",
    "abstract": "Dal 28 settembre al 10 ottobre, fra icone del brand e nuove collezioni, Giorgetti mette in scena il suo lifestyle."
  },
  {
    "id": 1,
    "country": {
      "id": 0,
      "name": "Italia"
    },
    "url": "https://www.giorgettimeda.com/it/events-news/2020-deloitte-best-managed-company",
    "image": "/giorgetti/img/news/7104_t_Giorgetti_We-did-it_2251x2251_news.jpg",
    "date": "14.9.2020",
    "title": "Giorgetti premiata come “Best Managed Company” anche nel 2020",
    "abstract": "Il premio è indetto da Deloitte per sostenere l’eccellenza del made in Italy."
  },
  {
    "id": 1,
    "country": {
      "id": 0,
      "name": "Italia"
    },
    "url": "https://www.giorgettimeda.com/it/events-news/adi-compasso-doro-marco-ferreri",
    "image": "/giorgetti/img/news/7089_t_screenshot-video120_news.jpg",
    "date": "11.9.2020",
    "title": "ADI Compasso d’Oro - Premio alla Carriera a Marco Ferreri",
    "abstract": "Giorgetti brinda al Compasso d’Oro alla carriera assegnato a Marco Ferreri."
  },
  {
    "id": 1,
    "country": {
      "id": 0,
      "name": "Italia"
    },
    "url": "https://www.giorgettimeda.com/it/events-news/adv-campaign-2020",
    "image": "/giorgetti/img/news/7084_t_Giorgetti_65I6223_news.jpg",
    "date": "10.9.2020",
    "title": "ADV Campaign 2020",
    "abstract": "Su “Voices” di Giorgetti Channel, la campagna pubblicitaria 2020."
  },
  {
    "id": 1,
    "country": {
      "id": 0,
      "name": "Italia"
    },
    "url": "https://www.giorgettimeda.com/it/events-news/materials-research-metal",
    "image": "/giorgetti/img/news/7065_t_news.jpg",
    "date": "3.9.2020",
    "title": "Materials research - special metal manufacturing",
    "abstract": "Su “Voices” di Giorgetti Channel, le lavorazioni del metallo nella collezione 2020."
  },
  {
    "id": 1,
    "country": {
      "id": 0,
      "name": "Italia"
    },
    "url": "https://www.giorgettimeda.com/it/events-news/atmosphere-art-and-fun",
    "image": "/giorgetti/img/news/7025_t_news.jpg",
    "date": "27.8.2020",
    "title": "Atmosphere - art and fun",
    "abstract": "Su “Voices” di Giorgetti Channel, la collezione Atmosphere 2020."
  },
  {
    "id": 1,
    "country": {
      "id": 0,
      "name": "Italia"
    },
    "url": "https://www.giorgettimeda.com/it/events-news/materials-research-fabric-and-leather_2",
    "image": "/giorgetti/img/news/7021_t_News_Azienda_056.jpg",
    "date": "25.8.2020",
    "title": "Materials research - fabric and leather",
    "abstract": "Su “Voices” di Giorgetti Channel, la seconda parte della ricerca condotta su tessuti e pelli per la collezione 2020."
  },
  {
    "id": 1,
    "country": {
      "id": 0,
      "name": "Italia"
    },
    "url": "https://www.giorgettimeda.com/it/events-news/materials-research-fabric-and-leather",
    "image": "/giorgetti/img/news/7011_t_CompanyProfile2013_028_news.jpg",
    "date": "31.7.2020",
    "title": "Materials research - fabric and leather",
    "abstract": "Su “Voices” di Giorgetti Channel, la ricerca condotta su tessuti e pelli per la collezione 2020."
  },
  {
    "id": 1,
    "country": {
      "id": 0,
      "name": "Italia"
    },
    "url": "https://www.giorgettimeda.com/it/events-news/special-ceramic-manufacturing",
    "image": "/giorgetti/img/news/6995_t_GIORGETTI-LENTATE_148-modif_news.jpg",
    "date": "29.7.2020",
    "title": "Special ceramic manufacturing",
    "abstract": "Su “Voices” di Giorgetti Channel, le lavorazioni della ceramica nella collezione 2020."
  },
  {
    "id": 1,
    "country": {
      "id": 0,
      "name": "Italia"
    },
    "url": "https://www.giorgettimeda.com/it/events-news/special-marble-manufacturing",
    "image": "/giorgetti/img/news/6969_t_Giorgetti_1K3G6219_news.jpg",
    "date": "24.7.2020",
    "title": "Special marble manufacturing",
    "abstract": "Su “Voices” di Giorgetti Channel, le lavorazioni del marmo nella collezione 2020."
  },
  {
    "id": 1,
    "country": {
      "id": 0,
      "name": "Italia"
    },
    "url": "https://www.giorgettimeda.com/it/events-news/pinkham-point-full-movie",
    "image": "/giorgetti/img/news/6966_t_Giorgetti_PinkhamPoint_Outdoor_06-news.jpg",
    "date": "23.7.2020",
    "title": "Pinkham Point",
    "abstract": "Su Giorgetti Channel va in onda l’intero film."
  },
  {
    "id": 1,
    "country": {
      "id": 0,
      "name": "Italia"
    },
    "url": "https://www.giorgettimeda.com/it/events-news/special-wood-manufacturing",
    "image": "/giorgetti/img/news/6943_t_CompanyProfile2013_002_news.jpg",
    "date": "22.7.2020",
    "title": "Special wood manufacturing",
    "abstract": "Su “Voices” di Giorgetti Channel, le lavorazioni del legno nella collezione 2020."
  },
  {
    "id": 1,
    "country": {
      "id": 0,
      "name": "Italia"
    },
    "url": "https://www.giorgettimeda.com/it/events-news/giorgetti-atelier-milan-2020",
    "image": "/giorgetti/img/news/6948_t_Giorgetti_Atelier_2020_255_HR-news.jpg",
    "date": "22.7.2020",
    "title": "Giorgetti rinnova l'Atelier milanese",
    "abstract": "Fra icone e nuove collezioni, il lifestyle Giorgetti nell’Atelier di Milano."
  },
  {
    "id": 1,
    "country": {
      "id": 0,
      "name": "Italia"
    },
    "url": "https://www.giorgettimeda.com/it/events-news/pinkham-point-06-the-outdoor",
    "image": "/giorgetti/img/news/6939_t_Giorgetti_PinkhamPoint_Outdoor_news.jpg",
    "date": "17.7.2020",
    "title": "Pinkham Point 06 The outdoor",
    "abstract": "Su Giorgetti Channel va in onda l'ultimo episodio del film."
  },
  {
    "id": 1,
    "country": {
      "id": 0,
      "name": "Italia"
    },
    "url": "https://www.giorgettimeda.com/it/events-news/pinkham-point-05-the-dressing-the-gym",
    "image": "/giorgetti/img/news/6910_t_Giorgetti_PinkhamPoint_Dressing Gym_02_news.jpg",
    "date": "10.7.2020",
    "title": "Pinkham Point 05 The dressing and the gym",
    "abstract": "Su Giorgetti Channel va in onda il quinto episodio del film."
  },
  {
    "id": 1,
    "country": {
      "id": 0,
      "name": "Italia"
    },
    "url": "https://www.giorgettimeda.com/it/events-news/voices-from-east-to-west_2",
    "image": "/giorgetti/img/news/6923_t_From_east_to_West-news-cover.jpg",
    "date": "9.7.2020",
    "title": "From East to West",
    "abstract": "In onda su Giorgetti Channel, “Voices”, con i nuovi designers 2020."
  },
  {
    "id": 1,
    "country": {
      "id": 0,
      "name": "Italia"
    },
    "url": "https://www.giorgettimeda.com/it/events-news/pinkham-point-04-the-bedroom",
    "image": "/giorgetti/img/news/6898_t_Giorgetti_PinkhamPoint_Bedroom_02-news.jpg",
    "date": "2.7.2020",
    "title": "Pinkham Point 04 The bedroom",
    "abstract": "Su Giorgetti Channel va in onda il quarto episodio del film."
  },
  {
    "id": 1,
    "country": {
      "id": 0,
      "name": "Italia"
    },
    "url": "https://www.giorgettimeda.com/it/events-news/pinkham-point-03-the-patio-and-the-studio",
    "image": "/giorgetti/img/news/6806_t_Giorgetti_superresolution_R_patio_03_2_modificata_HR-news.jpg",
    "date": "26.6.2020",
    "title": "Pinkham Point 03 The patio and the studio",
    "abstract": "Su Giorgetti Channel va in onda il terzo episodio del film."
  },
  {
    "id": 1,
    "country": {
      "id": 0,
      "name": "Italia"
    },
    "url": "https://www.giorgettimeda.com/it/events-news/pinkham-point-02-the-dining-and-the-kitchen",
    "image": "/giorgetti/img/news/6785_t_Giorgetti_PinkhamPoint_Dining Kitchen_02_default2.jpg",
    "date": "19.6.2020",
    "title": "Pinkham Point 02 The dining and the kitchen",
    "abstract": "Su Giorgetti Channel va in onda il secondo episodio del film."
  },
  {
    "id": 1,
    "country": {
      "id": 0,
      "name": "Italia"
    },
    "url": "https://www.giorgettimeda.com/it/events-news/pinkham-point-the-living",
    "image": "/giorgetti/img/news/6696_t_Giorgetti_PinkhamPoint_Living_02_default255.jpg",
    "date": "11.6.2020",
    "title": "Pinkham Point 01 The living",
    "abstract": "Al via il primo episodio del film per presentare le collezioni 2020."
  },
  {
    "id": 1,
    "country": {
      "id": 0,
      "name": "Italia"
    },
    "url": "https://www.giorgettimeda.com/it/events-news/pinkham-point",
    "image": "/giorgetti/img/news/6661_t_Giorgetti_PinkhamPoint_Living_01_default255.jpg",
    "date": "10.6.2020",
    "title": "Giorgetti presenta Pinkham Point",
    "abstract": "Sul nuovo canale digitale."
  },
  {
    "id": 1,
    "country": {
      "id": 0,
      "name": "Italia"
    },
    "url": "https://www.giorgettimeda.com/it/events-news/2020-restart",
    "image": "/giorgetti/img/news/6654_t_GDV_listingS.jpg",
    "date": "9.6.2020",
    "title": "2020 Restart",
    "abstract": "Giorgetti lancia un broadcast digitale per presentare la collezione 2020."
  },
  {
    "id": 1,
    "country": {
      "id": 0,
      "name": "Italia"
    },
    "url": "https://www.giorgettimeda.com/it/events-news/new-collection-2020-host",
    "image": "/giorgetti/img/news/6601_t_news-host.jpg",
    "date": "10.5.2020",
    "title": "HOST by Adam D. Tihany",
    "abstract": "New collection 2020: un compagno elegante nei momenti conviviali."
  },
  {
    "id": 1,
    "country": {
      "id": 0,
      "name": "Italia"
    },
    "url": "https://www.giorgettimeda.com/it/events-news/new-collection-2020-kiri",
    "image": "/giorgetti/img/news/6598_t_news.jpg",
    "date": "8.5.2020",
    "title": "KIRI by Setsu &amp; Shinobu Ito",
    "abstract": "New collection 2020: il fascino delle antiche usanze orientali."
  },
  {
    "id": 1,
    "country": {
      "id": 0,
      "name": "Italia"
    },
    "url": "https://www.giorgettimeda.com/it/events-news/new-collection-2020_2",
    "image": "/giorgetti/img/news/6586_t_news.jpg",
    "date": "5.5.2020",
    "title": "New Collection 2020",
    "abstract": "Introduzione ai nuovi prodotti 2020."
  },
  {
    "id": 1,
    "country": {
      "id": 0,
      "name": "Italia"
    },
    "url": "https://www.giorgettimeda.com/it/events-news/giorgetti-apre-un-nuovo-store-a-johannesburg",
    "image": "/giorgetti/img/news/6610_t_Store_Johannesburg_news.jpg",
    "date": "4.5.2020",
    "title": "GIORGETTI APRE UN NUOVO STORE A JOHANNESBURG",
    "abstract": "Giorgetti porta il Made in Italy anche in Sudafrica."
  },
  {
    "id": 1,
    "country": {
      "id": 0,
      "name": "Italia"
    },
    "url": "https://www.giorgettimeda.com/it/events-news/il-lifestyle-giorgetti-a-romanellhotel-westin-excelsior",
    "image": "/giorgetti/img/news/6578_t_Giorgetti_Villa_La_Cupola_Roma_news-LITTLE.jpg",
    "date": "30.4.2020",
    "title": "Giorgetti al Westin Excelsior Rome",
    "abstract": "Giorgetti partecipa al restyling di Villa La Cupola."
  },
  {
    "id": 1,
    "country": {
      "id": 0,
      "name": "Italia"
    },
    "url": "https://www.giorgettimeda.com/it/events-news/giorgetti-riavvia-la-produzione",
    "image": "/giorgetti/img/news/6575_t_Giorgetti_news.jpg",
    "date": "27.4.2020",
    "title": "Giorgetti riavvia la produzione",
    "abstract": "27 aprile 2020."
  },
  {
    "id": 1,
    "country": {
      "id": 0,
      "name": "Italia"
    },
    "url": "https://www.giorgettimeda.com/it/events-news/manifesto-per-la-riapertura-15-aprile",
    "image": "/giorgetti/img/news/6573_t_manifesto15_news.jpg",
    "date": "15.4.2020",
    "title": "Design manifesto",
    "abstract": "15 aprile 2020."
  },
  {
    "id": 1,
    "country": {
      "id": 0,
      "name": "Italia"
    },
    "url": "https://www.giorgettimeda.com/it/events-news/manifesto-per-la-riapertura",
    "image": "/giorgetti/img/news/6563_t_manifesto-covid_news.jpg",
    "date": "8.4.2020",
    "title": "Design manifesto",
    "abstract": "8 aprile 2020."
  },
  {
    "id": 1,
    "country": {
      "id": 0,
      "name": "Italia"
    },
    "url": "https://www.giorgettimeda.com/it/events-news/giorgetti-company-update",
    "image": "/giorgetti/img/news/6536_t_news-S.jpg",
    "date": "23.3.2020",
    "title": "Company update",
    "abstract": "23 marzo 2020."
  },
  {
    "id": 1,
    "country": {
      "id": 0,
      "name": "Italia"
    },
    "url": "https://www.giorgettimeda.com/it/events-news/giorgetti-apre-un-nuovo-store-a-new-delhi",
    "image": "/giorgetti/img/news/6535_t_Giorgetti_Store_NewDelhi_default_SMALL.jpg",
    "date": "15.2.2020",
    "title": "GIORGETTI APRE UN NUOVO STORE A NEW DELHI",
    "abstract": "Giorgetti porta il suo lifestyle in India."
  },
  {
    "id": 1,
    "country": {
      "id": 0,
      "name": "Italia"
    },
    "url": "https://www.giorgettimeda.com/it/events-news/giorgetti-rinnova-lo-spazio-a-bangkoktailandia",
    "image": "/giorgetti/img/news/6553_t_Eurocreation2020_news.jpg",
    "date": "1.2.2020",
    "title": "GIORGETTI RINNOVA LO SPAZIO A BANGKOK, TAILANDIA",
    "abstract": "Lo spazio Giorgetti a Bangkok, in Tailandia, si è rinnovato."
  },
  {
    "id": 1,
    "country": {
      "id": 0,
      "name": "Italia"
    },
    "url": "https://www.giorgettimeda.com/it/events-news/interior-mebel-2020kiev",
    "image": "/giorgetti/img/news/6411_t_Listing_GiorgettiInteriorMebel.jpg",
    "date": "26.1.2020",
    "title": "INTERIOR MEBEL 2020, KIEV",
    "abstract": "Il mondo Giorgetti arriva a Kiev, dal 5 al 9 febbraio, con la fiera Interior Mebel (Stand 3/3 – 42)."
  },
  {
    "id": 1,
    "country": {
      "id": 0,
      "name": "Italia"
    },
    "url": "https://www.giorgettimeda.com/it/events-news/giorgetti-partecipa-a-brafa-2020-con-la-galleria-darte-cortesi",
    "image": "/giorgetti/img/news/6398_t_BRAFA_ART_FAIR_listingd.jpg",
    "date": "23.1.2020",
    "title": "GIORGETTI E GALLERIA CORTESI A BRAFA 2020",
    "abstract": "Giorgetti è a Brafa, una delle più importanti fiere d’arte, a Bruxelles dal 26 gennaio al 2 febbraio."
  },
  {
    "id": 1,
    "country": {
      "id": 0,
      "name": "Italia"
    },
    "url": "https://www.giorgettimeda.com/it/events-news/best-moonlighting-wallpaper-design-awards2020",
    "image": "/giorgetti/img/news/6388_t_ALLAROUND_cover.jpg",
    "date": "20.1.2020",
    "title": "All Around è Best Moonlighting di Wallpaper Design Awards 2020",
    "abstract": "Wallpaper* assegna il premio “Best Moonlighting” alla poltrona All Around di Ludovica+Roberto Palomba."
  },
  {
    "id": 1,
    "country": {
      "id": 0,
      "name": "Italia"
    },
    "url": "https://www.giorgettimeda.com/it/events-news/giorgetti-mcy-duss-2020",
    "image": "/giorgetti/img/news/6290_t_MCY76_Mooring_slideshowlisting.jpg",
    "date": "8.1.2020",
    "title": "GIORGETTI CON MONTE CARLO YACHTS PER BOOT DÜSSELDORF",
    "abstract": "Giorgetti torna al Boot Düsseldorf, il salone nautico indoor in scena dal 18 al 26 gennaio 2020, in collaborazione con Monte Carlo Yachts."
  },
  {
    "id": 1,
    "country": {
      "id": 0,
      "name": "Italia"
    },
    "url": "https://www.giorgettimeda.com/it/events-news/trottole",
    "image": "/giorgetti/img/news/6526_t_news2.jpg",
    "date": "8.1.2020",
    "title": "LEGNO: UNA TRADIZIONE, UNA PASSIONE",
    "abstract": "L’ebanista milanese Luciano Molinari rende omaggio alla varietà delle essenze con cui Giorgetti dà vita alle sue collezioni realizzando preziose trottole in legno."
  },
  {
    "id": 1,
    "country": {
      "id": 0,
      "name": "Italia"
    },
    "url": "https://www.giorgettimeda.com/it/events-news/giorgetti-racconta-la-propria-passione-per-il-legno-a-paris-d%C3%A9co-off",
    "image": "/giorgetti/img/news/6270_t_listing.jpg",
    "date": "8.1.2020",
    "title": "GIORGETTI RACCONTA LA PROPRIA PASSIONE PER IL LEGNO A PARIS DÉCO OFF",
    "abstract": "Dal 16 al 20 gennaio torna Paris Déco Off, l’appuntamento parigino con le tendenze dell’interior design e dell’home decoration."
  },
  {
    "id": 1,
    "country": {
      "id": 0,
      "name": "Italia"
    },
    "url": "https://www.giorgettimeda.com/it/events-news/giorgetti-cologne-2020",
    "image": "/giorgetti/img/news/6240_t_eventinews_Cologne_cover.jpg",
    "date": "10.12.2019",
    "title": "GIORGETTI IMM.COLOGNE 2020",
    "abstract": "Il mondo Giorgetti arriva a Colonia, dal 13 al 19 gennaio: IMM 2020 e Store di Kaiser-Wilhelm Ring."
  },
  {
    "id": 1,
    "country": {
      "id": 0,
      "name": "Italia"
    },
    "url": "https://www.giorgettimeda.com/it/events-news/ipertesto",
    "image": "/giorgetti/img/news/6509_t_eventinews_ipertesto_LISTING-prova.jpg",
    "date": "4.12.2019",
    "title": "Giorgetti per “Ipertesto” di Ludovica+Roberto Palomba",
    "abstract": "La galleria d’arte Tommaso Calabro di Milano ospita la mostra “Ipertesto”."
  },
  {
    "id": 1,
    "country": {
      "id": 0,
      "name": "Italia"
    },
    "url": "https://www.giorgettimeda.com/it/events-news/giorgetti-partecipa-a-al-progetto-muse-dialoganti",
    "image": "/giorgetti/img/news/6193_t_eventinews_musedialog_LISTING.jpg",
    "date": "3.12.2019",
    "title": "GIORGETTI PARTECIPA AL PROGETTO “MUSE DIALOGANTI”",
    "abstract": "“10 sedute per 10 musei”: arte e design si uniscono nei musei di Milano."
  },
  {
    "id": 1,
    "country": {
      "id": 0,
      "name": "Italia"
    },
    "url": "https://www.giorgettimeda.com/it/events-news/campagna-adv-2020",
    "image": "/giorgetti/img/news/6130_t_eventinews_LISTING.jpg",
    "date": "28.11.2019",
    "title": "Nuova campagna pubblicitaria 2020: Object to project",
    "abstract": "Giorgetti lancia la nuova campagna pubblicitaria: design e architettura si intrecciano nell’esperienza dell’abitare per dar vita a un lifestyle ricercato, internazionale e senza tempo."
  },
  {
    "id": 1,
    "country": {
      "id": 0,
      "name": "Italia"
    },
    "url": "https://www.giorgettimeda.com/it/events-news/gk03-%C3%A8-best-kitchen-di-edida-china-2019-2020",
    "image": "/giorgetti/img/news/6127_t_elledecor19_GK03_LISTING.jpg",
    "date": "20.11.2019",
    "title": "GK.03 è Best Kitchen di EDIDA China 2019 - 2020",
    "abstract": "GK.03, in grado di definire lo spazio in un gioco di piani, prospettive e sovrapposizioni visive."
  },
  {
    "id": 1,
    "country": {
      "id": 72,
      "name": "Germania"
    },
    "url": "https://www.giorgettimeda.com/it/events-news/salone-del-mobileshanghai-2019",
    "image": "/giorgetti/img/news/6128_t_Giorgetti_eventinews_LISTING-shanghai.jpg",
    "date": "20.11.2019",
    "title": "Salone del Mobile.Shanghai 2019",
    "abstract": "Giorgetti racconta l’unicità del design italiano al Salone del Mobile di Shanghai dal 20 al 22 novembre 2019."
  },
  {
    "id": 1,
    "country": {
      "id": 0,
      "name": "Italia"
    },
    "url": "https://www.giorgettimeda.com/it/events-news/giorgetti-partecipa-al-progetto-di-vanadis-yacht",
    "image": "/giorgetti/img/news/6076_t_vanadis_ANTEPRIMA-news.jpg",
    "date": "9.10.2019",
    "title": "Giorgetti partecipa al progetto di Vanadis Yacht",
    "abstract": "Giorgetti partecipa al progetto di Vanadis Yacht con due prodotti iconici, Progetti e Ibla."
  },
  {
    "id": 1,
    "country": {
      "id": 72,
      "name": "Germania"
    },
    "url": "https://www.giorgettimeda.com/it/events-news/giorgetti-partecipa-al-progetto-dragon-yacht_2",
    "image": "/giorgetti/img/news/5987_t_dragon_opening_13_ANTEPRIMA.jpg",
    "date": "9.10.2019",
    "title": "Giorgetti partecipa al progetto Dragon Yacht",
    "abstract": "Giorgetti partecipa al progetto di Dragon con l’elegante tavolo Gordon."
  },
  {
    "id": 1,
    "country": {
      "id": 72,
      "name": "Germania"
    },
    "url": "https://www.giorgettimeda.com/it/events-news/giorgetti-apre-un-nuovo-showroom-in-cinaa-guangzhou",
    "image": "/giorgetti/img/news/5937_t_shunde_opening_13_ANTEPRIMA-min.jpg",
    "date": "29.9.2019",
    "title": "Giorgetti apre un nuovo showroom in Cina, a Guangzhou",
    "abstract": "Il lifestyle di Giorgetti si racconta in quasi 500 metri quadrati inaugurati il 29 settembre, all’interno del Louvre furniture mall, il nuovo tempio del design contemporaneo firmato da Carlo Colombo."
  },
  {
    "id": 1,
    "country": {
      "id": 72,
      "name": "Germania"
    },
    "url": "https://www.giorgettimeda.com/it/events-news/giorgetti-a-londra-per-i-made_2",
    "image": "/giorgetti/img/news/5863_t_I-MADE-2019_01-min.jpg",
    "date": "19.9.2019",
    "title": "Giorgetti a Londra per I-Made",
    "abstract": "In scena alla Saatchi Gallery di Chelsea, dal 19 al 22 settembre 2019, Giorgetti è protagonista di I-MADE, il nuovo appuntamento espositivo che racconta l’eccellenza del design Made in Italy nel contesto del London Design Festival."
  },
  {
    "id": 1,
    "country": {
      "id": 72,
      "name": "Germania"
    },
    "url": "https://www.giorgettimeda.com/it/events-news/giorgetti-torna-al-salone-nautico_2",
    "image": "/giorgetti/img/news/5870_t_SALONE_NAUTICO_05a.jpg",
    "date": "19.9.2019",
    "title": "Giorgetti torna al Salone Nautico",
    "abstract": "In occasione della 59esima edizione del Salone Nautico in scena dal 19 al 24 settembre, Giorgetti è protagonista della Vip Lounge del boat show."
  },
  {
    "id": 1,
    "country": {
      "id": 72,
      "name": "Germania"
    },
    "url": "https://www.giorgettimeda.com/it/events-news/giorgetti-paris-si-rinnova-per-la-paris-design-week",
    "image": "/giorgetti/img/news/5856_t_PARIGI_00.jpg",
    "date": "11.9.2019",
    "title": "Giorgetti Paris si rinnova per la Paris Design Week",
    "abstract": "A un anno dall’apertura del primo monobrand in Francia, Giorgetti è di nuovo protagonista nella Ville Lumière in occasione della Paris design Week."
  },
  {
    "id": 1,
    "country": {
      "id": 72,
      "name": "Germania"
    },
    "url": "https://www.giorgettimeda.com/it/events-news/mostra-itinerante-%E2%80%9Cobject-to-project%E2%80%9D",
    "image": "/giorgetti/img/news/5797_t_120thoff_quadrata-min.jpg",
    "date": "26.7.2019",
    "title": "Mostra itinerante “object to project”",
    "abstract": "Iniziato con la presentazione del nuovo logo, il brand conclude questo anno di festeggiamenti con la mostra itinerante allestita nei principali showroom e store Giorgetti, fra Asia, Stati Uniti ed Europa."
  },
  {
    "id": 1,
    "country": {
      "id": 72,
      "name": "Germania"
    },
    "url": "https://www.giorgettimeda.com/it/events-news/giorgetti-arreda-il-nuovo-mcy-76",
    "image": "/giorgetti/img/news/5746_t_MCY76_00-min.jpg",
    "date": "23.7.2019",
    "title": "GIORGETTI ARREDA IL NUOVO MCY 76",
    "abstract": "Il terzo yacht dell'attesa nuova generazione di imbarcazioni MCY è stato presentato a luglio nel Golfo di Trieste, insieme al MCY 70 e al MCY 66."
  },
  {
    "id": 1,
    "country": {
      "id": 72,
      "name": "Germania"
    },
    "url": "https://www.giorgettimeda.com/it/events-news/object-to-project-arriva-a-hong-kong-il-27-giugno-2019",
    "image": "/giorgetti/img/news/5725_t_HongKong-min.jpg",
    "date": "27.6.2019",
    "title": "OBJECT TO PROJECT ARRIVA A HONG KONG IL 27 GIUGNO 2019",
    "abstract": "Il monobrand Giorgetti aperto a novembre 2018 nel distretto di Wan Chai, realizzato con il supporto di E.Bon, ospita l’esposizione e la proiezione dell’omonimo film diretto da Muse Factory of Projects."
  },
  {
    "id": 1,
    "country": {
      "id": 72,
      "name": "Germania"
    },
    "url": "https://www.giorgettimeda.com/it/events-news/giorgetti-apre-un-nuovo-store-a-boston_2",
    "image": "/giorgetti/img/news/5663_t_StoreBoston-min.jpg",
    "date": "23.5.2019",
    "title": "GIORGETTI APRE UN NUOVO STORE A BOSTON",
    "abstract": "Giorgetti, brand leader del design made in Italy, consolida la propria posizione di rilievo negli Stati Uniti con l’apertura di un nuovo monomarca a Boston, nel cuore pulsante di SoWa Art + Design District."
  },
  {
    "id": 1,
    "country": {
      "id": 72,
      "name": "Germania"
    },
    "url": "https://www.giorgettimeda.com/it/events-news/mostra-object-to-project-a-ho-chi-minh-city",
    "image": "/giorgetti/img/news/5682_t_HoChiMinh-min.jpg",
    "date": "23.5.2019",
    "title": "MOSTRA OBJECT TO PROJECT A HO CHI MINH CITY",
    "abstract": "Dopo aver celebrato i suoi 120 anni con un variegato programma di iniziative culturali, Giorgetti continua a promuovere la cultura del design di alta qualità con Object to Project, la mostra itinerante che arriva a Ho Chi Minh City il 23 maggio 2019."
  },
  {
    "id": 1,
    "country": {
      "id": 72,
      "name": "Germania"
    },
    "url": "https://www.giorgettimeda.com/it/events-news/salone-del-mobile-milano-2019",
    "image": "/giorgetti/img/news/5539_t_A_GIORGETTI-min.jpg",
    "date": "9.4.2019",
    "title": "SALONE DEL MOBILE . MILANO 2019",
    "abstract": "In occasione del Salone del Mobile di Milano 2019 Giorgetti racconta una visione dell’abitare che sempre più spesso si alimenta nelle contaminazioni creative."
  },
  {
    "id": 1,
    "country": {
      "id": 72,
      "name": "Germania"
    },
    "url": "https://www.giorgettimeda.com/it/events-news/mostra-object-to-project-a-colonia",
    "image": "/giorgetti/img/news/5147_t_A_Giorgetti_Colonia-min.jpg",
    "date": "28.3.2019",
    "title": "MOSTRA OBJECT TO PROJECT A COLONIA",
    "abstract": "Una settimana dopo la tappa di Jakarta, Giorgetti ha portato la mostra itinerante Object to Project a Colonia, esattamente il 28 marzo 2019."
  },
  {
    "id": 1,
    "country": {
      "id": 72,
      "name": "Germania"
    },
    "url": "https://www.giorgettimeda.com/it/events-news/mostra-object-to-project-a-jakarta",
    "image": "/giorgetti/img/news/5113_t_A_Giorgetti_Jakarta-min.jpg",
    "date": "21.3.2019",
    "title": "MOSTRA OBJECT TO PROJECT A JAKARTA",
    "abstract": "Giorgetti continua a promuovere la cultura del design di qualità con Object to Project, la mostra itinerante che, dopo le tappe di Città del Messico, Shanghai, Copenhagen, Pechino e Parigi, ha debuttato il 21 marzo 2019 a Jakarta."
  },
  {
    "id": 1,
    "country": {
      "id": 72,
      "name": "Germania"
    },
    "url": "https://www.giorgettimeda.com/it/events-news/giorgetti-protagonista-al-salone-dellauto-con-maserati",
    "image": "/giorgetti/img/news/5086_t_A_Giorgetti_Maserati_2-min.jpg",
    "date": "5.3.2019",
    "title": "GIORGETTI PROTAGONISTA AL SALONE DELL'AUTO CON MASERATI",
    "abstract": "In occasione del Salone dell'Auto di Ginevra 2019 (dal 7 al 17 marzo), Giorgetti svela i segreti della lavorazione del legno in uno speciale allestimento nello stand Maserati che esalta l’artigianalità del marchio, e arreda due eleganti lounge."
  },
  {
    "id": 1,
    "country": {
      "id": 72,
      "name": "Germania"
    },
    "url": "https://www.giorgettimeda.com/it/events-news/a-parigi-la-mostra-itinerante-object-to-project",
    "image": "/giorgetti/img/news/5047_t_A_120thParigi_.jpg",
    "date": "21.1.2019",
    "title": "A PARIGI LA MOSTRA ITINERANTE OBJECT TO PROJECT",
    "abstract": "Giorgetti continua a promuovere la cultura del design di qualità con Object to Project, la mostra itinerante che, dopo la tappa di dicembre 2018 da Classic Living a Pechino, ha debuttato il 21 gennaio 2019 a Parigi."
  },
  {
    "id": 1,
    "country": {
      "id": 72,
      "name": "Germania"
    },
    "url": "https://www.giorgettimeda.com/it/events-news/giorgetti-al-boat-show-a-d%C3%BCsseldorf-con-monte-carlo-yachts_4",
    "image": "/giorgetti/img/news/5031_t_A_MCY.jpg",
    "date": "19.1.2019",
    "title": "GIORGETTI AL BOAT SHOW A DÜSSELDORF CON MONTE CARLO YACHTS",
    "abstract": "Continua la stretta collaborazione di Giorgetti con Monte Carlo Yachts. In scena dal 19 al 27 gennaio 2019, boot Düsseldorf è il Salone Nautico Internazionale indoor più grande al mondo e si svolge proprio nella capitale del Land della Renania Settentrionale-Vestfalia, in Germania."
  },
  {
    "id": 1,
    "country": {
      "id": 72,
      "name": "Germania"
    },
    "url": "https://www.giorgettimeda.com/it/events-news/giorgetti-protagonista-a-colonia",
    "image": "/giorgetti/img/news/5002_t_A_IMM_Colonia_2019.jpg",
    "date": "14.1.2019",
    "title": "GIORGETTI PROTAGONISTA A COLONIA",
    "abstract": "Giorgetti è stata protagonista a IMM 2019, in fiera dal 14 al 20 gennaio scorso, e nello Store di Kaiser-Wilhelm Ring, per raccontare una visione dell’abitare fatta di eleganza funzionale e contaminazioni."
  },
  {
    "id": 1,
    "country": {
      "id": 95,
      "name": "Regno Unito"
    },
    "url": "https://www.giorgettimeda.com/it/events-news/giorgetti-vince-ledizione-2019-del-wallpaper-design-award",
    "image": "/giorgetti/img/news/4985_t_A_WallpaperAward-min.jpg",
    "date": "1.1.2019",
    "title": "GIORGETTI VINCE L’EDIZIONE 2019 DEL WALLPAPER* DESIGN AWARD",
    "abstract": "Il carrello Alfred è stato giudicato dall’autorevole magazine inglese come “Best meals on wheels”, dimostrando l’impegno e la serietà con cui Giorgetti è entrata nel comparto delle cucine."
  },
  {
    "id": 1,
    "country": {
      "id": 204,
      "name": "Stati Uniti d'America"
    },
    "url": "https://www.giorgettimeda.com/it/events-news/giorgetti-scommette-sulla-danimarca",
    "image": "/giorgetti/img/news/4798_t_Interstudio_Copenaghen-min.jpg",
    "date": "28.11.2018",
    "title": "GIORGETTI SCOMMETTE SULLA DANIMARCA",
    "abstract": "Giorgetti porta il design made in Italy in Nord Europa con un nuovo spazio nel centro Copenaghen, nel distretto internazionale della moda e del design."
  },
  {
    "id": 1,
    "country": {
      "id": 204,
      "name": "Stati Uniti d'America"
    },
    "url": "https://www.giorgettimeda.com/it/events-news/giorgetti-store-inaugura-a-hong-kong",
    "image": "/giorgetti/img/news/4806_t_HongKong-min.jpg",
    "date": "27.11.2018",
    "title": "GIORGETTI STORE INAUGURA A HONG KONG",
    "abstract": "Giorgetti continua a investire sul mercato asiatico con l’apertura del primo monobrand di Hong Kong, nel distretto di Wan Chai: questo store consolida la presenza dell’azienda in Oriente e offre un’esperienza completa dell’abitare firmato Giorgetti, che i clienti locali hanno già potuto apprezzare grazie a uno shop in shop situato nel design store ViA, a pochi passi dal nuovo negozio."
  },
  {
    "id": 1,
    "country": {
      "id": 204,
      "name": "Stati Uniti d'America"
    },
    "url": "https://www.giorgettimeda.com/it/events-news/la-mostra-object-to-project-arriva-a-shanghai",
    "image": "/giorgetti/img/news/4812_t_Shanghai-min.jpg",
    "date": "23.11.2018",
    "title": "LA MOSTRA OBJECT TO PROJECT ARRIVA A SHANGHAI",
    "abstract": "La mostra itinerante Object to Project, dopo la prima tappa di Città del Messico, è approdata a Shanghai in concomitanza con il Salone del Mobile asiatico."
  },
  {
    "id": 1,
    "country": {
      "id": 204,
      "name": "Stati Uniti d'America"
    },
    "url": "https://www.giorgettimeda.com/it/events-news/salone-del-mobile-milano-shanghai-2018",
    "image": "/giorgetti/img/news/4790_t_Shanghai-min.jpg",
    "date": "22.11.2018",
    "title": "SALONE DEL MOBILE. MILANO SHANGHAI 2018",
    "abstract": "Giorgetti è stata protagonista al Salone del Mobile di Shanghai in scena dal 22 al 24 novembre 2018."
  },
  {
    "id": 1,
    "country": {
      "id": 204,
      "name": "Stati Uniti d'America"
    },
    "url": "https://www.giorgettimeda.com/it/events-news/giorgetti-store-milano-si-rinnova",
    "image": "/giorgetti/img/news/4757_t_StoreMilano-min.jpg",
    "date": "26.10.2018",
    "title": "GIORGETTI STORE MILANO SI RINNOVA",
    "abstract": "In occasione della Fall Design Week milanese, lo Store Giorgetti in centro città, in via Durini, si è rinnovato."
  },
  {
    "id": 1,
    "country": {
      "id": 204,
      "name": "Stati Uniti d'America"
    },
    "url": "https://www.giorgettimeda.com/it/events-news/giorgetti-al-milano-design-film-festival",
    "image": "/giorgetti/img/news/4752_t_milano_film-min.jpg",
    "date": "25.10.2018",
    "title": "GIORGETTI AL MILANO DESIGN FILM FESTIVAL",
    "abstract": "Giorgetti è stata protagonista del Milano Design Film Festival, in scena dal 25 al 28 ottobre 2018, negli spazi dell’Anteo Palazzo del Cinema, con il film dal titolo Object to Project: Giorgetti Design since 1898."
  },
  {
    "id": 1,
    "country": {
      "id": 204,
      "name": "Stati Uniti d'America"
    },
    "url": "https://www.giorgettimeda.com/it/events-news/la-mostra-itinerante-object-to-project-parte-da-citta-del-messico_2",
    "image": "/giorgetti/img/news/4724_t_120thMexico_1.jpg",
    "date": "15.10.2018",
    "title": "LA MOSTRA ITINERANTE OBJECT TO PROJECT PARTE DA CITTA’ DEL MESSICO",
    "abstract": "Giorgetti è giunta all’ultimo appuntamento del ricco programma di iniziative culturali ideate per celebrare i 120 anni dell’azienda."
  },
  {
    "id": 1,
    "country": {
      "id": 72,
      "name": "Germania"
    },
    "url": "https://www.giorgettimeda.com/it/events-news/giorgetti-2019-campagna-adv_2",
    "image": "/giorgetti/img/news/5771_t_DEFINITIVA_255x255.jpg",
    "date": "12.10.2018",
    "title": "Nuova creatività per la campagna adv 2019",
    "abstract": "Il quinto capitolo del progetto di comunicazione visiva “How Different Would You Be?” mette in primo piano il living e racconta ancora una volta la capacità di Giorgetti di far incontrare epoche e stili."
  },
  {
    "id": 1,
    "country": {
      "id": 204,
      "name": "Stati Uniti d'America"
    },
    "url": "https://www.giorgettimeda.com/it/events-news/giorgetti-al-salone-nautico-di-genova",
    "image": "/giorgetti/img/news/4698_t_SaloneNauticoGenova_12-min.jpg",
    "date": "3.10.2018",
    "title": "GIORGETTI AL SALONE NAUTICO DI GENOVA",
    "abstract": "In occasione della 58esima edizione del Salone Nautico di Genova, andato in scena dal 20 al 25 settembre, Giorgetti è stata protagonista della Vip Lounge del polo espositivo con un progetto di interior design che ha raccontato anche nell’ambito della nautica da diporto l’unicità della manifattura made in Italy e l’applicazione di soluzioni innovative nelle diverse esperienze dell’abitare."
  },
  {
    "id": 1,
    "country": {
      "id": 204,
      "name": "Stati Uniti d'America"
    },
    "url": "https://www.giorgettimeda.com/it/events-news/primo-store-francese-per-giorgetti_2",
    "image": "/giorgetti/img/news/4685_t_Paris_Giorgetti 11-min.jpg",
    "date": "13.9.2018",
    "title": "PRIMO STORE FRANCESE PER GIORGETTI",
    "abstract": "A Parigi nel cuore di Saint-Germain-des-Prés, Giorgetti ha aperto il suo primo monobrand in Francia. Al numero 10 di Rue de l’Abbaye, Giorgetti offre un’esperienza unica dell’abitare: quella che ha definito in 120 anni di storia con collezioni d’arredo in grado di rispondere a ogni esigenza di stile, funzionalità e qualità."
  },
  {
    "id": 1,
    "country": {
      "id": 204,
      "name": "Stati Uniti d'America"
    },
    "url": "https://www.giorgettimeda.com/it/events-news/design-italiano-a-foshan_3",
    "image": "/giorgetti/img/news/4678_t_Foshan_ Giorgetti-min.jpg",
    "date": "10.9.2018",
    "title": "DESIGN ITALIANO A FOSHAN",
    "abstract": "Grande manifestazione dedicata al design italiano in Cina. A Foshan lo scorso 8 settembre 2018, il rivenditore Shunde Louvre ha festeggiato l’arrivo delle nuove collezioni d’arredamento Made in Italy con una particolare cerimonia e con l’intervento di importanti architetti."
  },
  {
    "id": 1,
    "country": {
      "id": 204,
      "name": "Stati Uniti d'America"
    },
    "url": "https://www.giorgettimeda.com/it/events-news/premio-imprenditore-40-design_2",
    "image": "/giorgetti/img/news/4597_t_Imprenditore 4.0 Design_ Giorgetti 2-min.jpg",
    "date": "1.7.2018",
    "title": "PREMIO IMPRENDITORE 4.0 - DESIGN",
    "abstract": "“E’ la tecnologia al servizio della sapienza delle mani, è la capacità di mettere insieme la techne della competenza manifatturiera con lo sguardo creativo della grande cultura”."
  },
  {
    "id": 1,
    "country": {
      "id": 204,
      "name": "Stati Uniti d'America"
    },
    "url": "https://www.giorgettimeda.com/it/events-news/giorgetti-acquisisce-battaglia-interior-contractors",
    "image": "/giorgetti/img/news/4582_t_Battaglia_1.jpg",
    "date": "29.6.2018",
    "title": "GIORGETTI ACQUISISCE BATTAGLIA INTERIOR CONTRACTORS",
    "abstract": "Giorgetti consolida la propria strategia di crescita nell’ambito del contract e annuncia l’acquisizione del 100% di Battaglia Interior Contractors."
  },
  {
    "id": 1,
    "country": {
      "id": 204,
      "name": "Stati Uniti d'America"
    },
    "url": "https://www.giorgettimeda.com/it/events-news/nuove-collezioni-da-ddc-a-new-york_2",
    "image": "/giorgetti/img/news/4532_t_NY_002.jpg",
    "date": "14.5.2018",
    "title": "NUOVE COLLEZIONI DA DDC A NEW YORK",
    "abstract": "Giorgetti presenta a New York le nuove collezioni lanciate al Salone del Mobile di Milano ad aprile, in occasione di ICFF 2018, il più importante evento del Nord America dedicato all’interior design e all’architettura."
  },
  {
    "id": 1,
    "country": {
      "id": 204,
      "name": "Stati Uniti d'America"
    },
    "url": "https://www.giorgettimeda.com/it/events-news/giorgetti-al-salone-del-mobile-milano-2018",
    "image": "/giorgetti/img/news/4497_t_Giorgetti Stand 2018.jpg",
    "date": "17.4.2018",
    "title": "GIORGETTI AL SALONE DEL MOBILE . MILANO 2018",
    "abstract": "Giorgetti compie 120 anni e festeggia questo importante compleanno in occasione del Salone del Mobile 2018 con straordinari progetti che raccontano la storia del brand."
  },
  {
    "id": 1,
    "country": {
      "id": 204,
      "name": "Stati Uniti d'America"
    },
    "url": "https://www.giorgettimeda.com/it/events-news/giorgetti-a-homedepotvienna_2",
    "image": "/giorgetti/img/news/4065_t_HOMEDEPOT_Vienna2018_004-min.jpg",
    "date": "14.3.2018",
    "title": "GIORGETTI A H.O.M.E.D.E.P.O.T., VIENNA",
    "abstract": "Giorgetti ha partecipato a H.O.M.E. D.E.P.O.T., l’annuale fiera dedicata al mondo dell’arredo organizzata dalla rivista austriaca H.O.M.E."
  },
  {
    "id": 1,
    "country": {
      "id": 204,
      "name": "Stati Uniti d'America"
    },
    "url": "https://www.giorgettimeda.com/it/events-news/giorgetti-protagonista-a-stoccarda",
    "image": "/giorgetti/img/news/4045_t_IMG_9002.jpg",
    "date": "1.3.2018",
    "title": "GIORGETTI PROTAGONISTA A STOCCARDA",
    "abstract": "Fleiner Möbel by architare ha ospitato lo scorso 1 marzo 2018 un evento dedicato a Giorgetti, dedicando due vetrine e una parte del suo spazio espositivo a Stoccarda alle ultime collezioni dell’azienda."
  },
  {
    "id": 1,
    "country": {
      "id": 204,
      "name": "Stati Uniti d'America"
    },
    "url": "https://www.giorgettimeda.com/it/events-news/giorgetti-store-a-houston-nuova-apertura",
    "image": "/giorgetti/img/news/4034_t_StoreHouston_010.jpg",
    "date": "15.2.2018",
    "title": "GIORGETTI STORE A HOUSTON: NUOVA APERTURA",
    "abstract": "Giorgetti riconferma la propria strategia di consolidamento nel mercato americano con l'apertura di un monobrand negli spazi di Casa, il nuovo megastore di Houston dedicato all'arredo di qualità."
  },
  {
    "id": 1,
    "country": {
      "id": 204,
      "name": "Stati Uniti d'America"
    },
    "url": "https://www.giorgettimeda.com/it/events-news/giorgetti-al-boat-show-a-d%C3%BCsseldorf-con-monte-carlo-yachts_2",
    "image": "/giorgetti/img/news/3989_t_A_MCY-min.jpg",
    "date": "20.1.2018",
    "title": "GIORGETTI AL BOAT SHOW A DÜSSELDORF CON MONTE CARLO YACHTS",
    "abstract": "Continua la stretta collaborazione di Giorgetti con Monte Carlo Yachts."
  },
  {
    "id": 1,
    "country": {
      "id": 204,
      "name": "Stati Uniti d'America"
    },
    "url": "https://www.giorgettimeda.com/it/events-news/labitare-contemporaneo-di-giorgetti-a-imm-2018",
    "image": "/giorgetti/img/news/3719_t_A_IMMcolonia.jpg",
    "date": "15.1.2018",
    "title": "L’ABITARE CONTEMPORANEO DI GIORGETTI A IMM 2018",
    "abstract": "Presentando una raffinata esperienza dell’abitare, Giorgetti è protagonista a IMM 2018 a Colonia dal 15 al 21 gennaio 2018, con uno spazio espositivo (Halle 11.1, stand B20-C21 e B26-C35) raddoppiato rispetto a quello dell’anno precedente."
  },
  {
    "id": 1,
    "country": {
      "id": 204,
      "name": "Stati Uniti d'America"
    },
    "url": "https://www.giorgettimeda.com/it/events-news/giorgetti-celebra-120-anni",
    "image": "/giorgetti/img/news/3828_t_A_LOGO120.jpg",
    "date": "1.1.2018",
    "title": "Giorgetti celebra 120 anni",
    "abstract": "Giorgetti, brand leader del design contemporaneo, compie 120 anni e per festeggiare questo importante anniversario ha ideato un nuovo logo che racconta l’unicità della manifattura Made in Italy, con la pulizia stilistica tipica delle collezioni dell’azienda. Con questo pittogramma il marchio si rinnova nell’immagine e consolida la propria identità che ha costruito nel tempo."
  },
  {
    "id": 1,
    "country": {
      "id": 204,
      "name": "Stati Uniti d'America"
    },
    "url": "https://www.giorgettimeda.com/it/events-news/progetti-fashion-news",
    "image": "/giorgetti/img/news/3684_t_ProgettiFashion2017_000-min.jpg",
    "date": "28.11.2017",
    "title": "PROGETTI FASHION",
    "abstract": "Giorgetti presenta con Agnona la collezione Progetti Fashion, il terzo capitolo di Progetti 30, l’iniziativa che celebra i trent’anni della collezione: una serie di oggetti da collezionare, che rispondono con stile e personalità al desiderio di unicità."
  },
  {
    "id": 1,
    "country": {
      "id": 204,
      "name": "Stati Uniti d'America"
    },
    "url": "https://www.giorgettimeda.com/it/events-news/giorgetti-houston",
    "image": "/giorgetti/img/news/104_t_LISTING_houston.jpg",
    "date": "1.9.2016",
    "title": "Giorgetti Houston",
    "abstract": "Giorgetti firma il primo progetto di real estate con un prestigioso building che sorgerà nell’upper kirby district di Houston, in Texas. Giorgetti Houston è il nome di questo edificio che si svilupperà su 7 piani e presenterà 32 unità abitative di ampio respiro che permetteranno all’azienda di esprimere al meglio la propria eccellenza progettuale."
  }
]
